stdarray.py
stdio.py
stdrandom.py
stdstats.py
su_stdlibs_python_coderunner-0.0.1.dist-info/LICENSE
su_stdlibs_python_coderunner-0.0.1.dist-info/METADATA
su_stdlibs_python_coderunner-0.0.1.dist-info/WHEEL
su_stdlibs_python_coderunner-0.0.1.dist-info/top_level.txt
su_stdlibs_python_coderunner-0.0.1.dist-info/RECORD
