Metadata-Version: 2.1
Name: su-stdlibs-python-coderunner
Version: 0.0.1
Summary: Stellenbosch University Python 3 CodeRunner code for "Introduction to Programming in Python, 1st Edition" by Sedgewick and Wayne
Author: Marcel Dunaiski
Author-email: marceldunaiski@sun.ac.za
License: GNU General Public License v3 (GPLv3)
Platform: any
Classifier: License :: OSI Approved :: GNU General Public License v3 (GPLv3)
Classifier: Operating System :: OS Independent
Classifier: Natural Language :: English
Classifier: Programming Language :: Python
Classifier: Programming Language :: Python :: 3
Classifier: Topic :: Utilities
Classifier: Intended Audience :: Education
Classifier: Intended Audience :: Science/Research
Classifier: Topic :: Software Development :: Libraries :: Python Modules
Requires-Python: >=3.8
License-File: LICENSE
Provides-Extra: dev
Requires-Dist: pytest ; extra == 'dev'
Requires-Dist: pytest-cov ; extra == 'dev'
Requires-Dist: coveralls ; extra == 'dev'
